{
  "id": "yk-vip-channel-identityarea",
  "type": "gaia-template",
  "exp-version": "V1",
  "layers": [
    {
      "id": "avatar",
      "type": "image"
    },
    {
      "id": "titleView",
      "type": "view",
      "layers": [
        {
          "id": "nameView",
          "type": "view",
          "layers": [
            {
              "id": "title",
              "type": "text"
            }
          ]
        }
      ]
    },
    {
      "id": "button",
      "type": "view"
    }
  ]
}
